<?xml version="1.0" ?>

<container xmlns="http://symfony.com/schema/dic/services"
    xmlns:xsi="http://www.w3.org/2001/XMLSchema-instance"
    xsi:schemaLocation="http://symfony.com/schema/dic/services http://symfony.com/schema/dic/services/services-1.0.xsd">


    <services>
     <service id="sonata.admin.manager.orm.tree" class="Iphp\TreeBundle\Admin\ModelManager">
           <argument type="service" id="doctrine" />
     </service>
    <!--
     <service id="sonata.admin.builder.orm_datagrid.tree" class="Iphp\TreeBundle\Admin\DatagridBuilder">
                    <argument type="service" id="form.factory" />
                    <argument type="service" id="sonata.admin.builder.filter.factory" />
                    <argument type="service" id="sonata.admin.guesser.orm_datagrid_chain" />
     </service>
 -->
    </services>
</container>
